src/__init__.py
src/__main__.py
src/app/__init__.py
src/app/server.py
src/capabilities/__init__.py
src/capabilities/prompts.py
src/capabilities/tools.py
src/domain/__init__.py
src/domain/exceptions.py
src/domain/models.py
src/services/__init__.py
src/services/chart_generator_factory.py
src/services/chart_service.py
src/services/configuration_service.py
src/visualization/__init__.py
src/visualization/chart_config.py
src/visualization/constants.py
src/visualization/field_validator.py
src/visualization/generator.py
src/visualization/mermaid_generator.py
mcp_plots-0.0.2.dist-info/METADATA
mcp_plots-0.0.2.dist-info/WHEEL
mcp_plots-0.0.2.dist-info/entry_points.txt
mcp_plots-0.0.2.dist-info/licenses/LICENSE
mcp_plots-0.0.2.dist-info/RECORD
