Metadata-Version: 2.4
Name: mcp-plots
Version: 0.0.2
Summary: MCP server for data visualization with Mermaid-first approach for Cursor and other MCP clients
Author: MCP Plots Team
License: MIT
License-File: LICENSE
Keywords: ai-tools,charts,cursor,data-analysis,mcp,mermaid,plotting,visualization
Classifier: Development Status :: 3 - Alpha
Classifier: Environment :: Console
Classifier: Intended Audience :: Developers
Classifier: Programming Language :: Python :: 3
Classifier: Programming Language :: Python :: 3.10
Classifier: Programming Language :: Python :: 3.11
Classifier: Programming Language :: Python :: 3.12
Classifier: Topic :: Scientific/Engineering :: Artificial Intelligence
Classifier: Topic :: Scientific/Engineering :: Visualization
Classifier: Topic :: Software Development :: Libraries :: Python Modules
Classifier: Topic :: Text Processing :: Markup
Requires-Python: >=3.10
Requires-Dist: matplotlib>=3.5.0
Requires-Dist: mcp>=1.0.0
Requires-Dist: numpy>=1.21.0
Requires-Dist: pandas>=1.3.0
Requires-Dist: seaborn>=0.11.0
Requires-Dist: tabulate>=0.9.0
Provides-Extra: dev
Requires-Dist: black>=22.0.0; extra == 'dev'
Requires-Dist: isort>=5.10.0; extra == 'dev'
Requires-Dist: mypy>=0.950; extra == 'dev'
Requires-Dist: pytest>=7.0.0; extra == 'dev'
